ursus/__init__.py
ursus/config.py
ursus/py.typed
ursus/server.py
ursus/utils.py
ursus/context_processors/__init__.py
ursus/context_processors/get_entries.py
ursus/context_processors/git_date.py
ursus/context_processors/image.py
ursus/context_processors/markdown.py
ursus/context_processors/related.py
ursus/context_processors/stale.py
ursus/generators/__init__.py
ursus/generators/static.py
ursus/linters/__init__.py
ursus/linters/footnotes.py
ursus/linters/images.py
ursus/linters/markdown.py
ursus/renderers/__init__.py
ursus/renderers/image.py
ursus/renderers/jinja.py
ursus/renderers/lunr.py
ursus/renderers/sass.py
ursus/renderers/static.py
ursus_ssg-1.4.3.data/scripts/ursus
ursus_ssg-1.4.3.dist-info/licenses/LICENSE
ursus_ssg-1.4.3.dist-info/METADATA
ursus_ssg-1.4.3.dist-info/WHEEL
ursus_ssg-1.4.3.dist-info/entry_points.txt
ursus_ssg-1.4.3.dist-info/top_level.txt
ursus_ssg-1.4.3.dist-info/RECORD
