Metadata-Version: 2.4
Name: ursus_ssg
Version: 1.4.3
Summary: Static site generator
Home-page: http://github.com/all-about-berlin/ursus
Author: Nicolas Bouliane
Author-email: contact@nicolasbouliane.com
License: MIT
Requires-Python: >=3.11
License-File: LICENSE
Requires-Dist: GitPython==3.1.45
Requires-Dist: imagesize==1.4.1
Requires-Dist: Jinja2==3.1.6
Requires-Dist: jinja2-simple-tags==0.6.1
Requires-Dist: libsass==0.23.0
Requires-Dist: lunr==0.8.0
Requires-Dist: Markdown==3.5.2
Requires-Dist: MarkupSafe==2.1.5
Requires-Dist: ordered-set==4.1.0
Requires-Dist: platformdirs==4.3.8
Requires-Dist: PyMuPDF==1.26.3
Requires-Dist: Pillow==11.3.0
Requires-Dist: watchdog==4.0.1
Requires-Dist: requests==2.32.4
Requires-Dist: rjsmin==1.2.4
Requires-Dist: rcssmin==1.2.1
Dynamic: author
Dynamic: author-email
Dynamic: description
Dynamic: description-content-type
Dynamic: home-page
Dynamic: license
Dynamic: license-file
Dynamic: requires-dist
Dynamic: requires-python
Dynamic: summary
